voicetype/__init__.py
voicetype/__main__.py
voicetype/_version.py
voicetype/app_context.py
voicetype/error_log.txt
voicetype/install.py
voicetype/settings.py
voicetype/state.py
voicetype/trayicon.py
voicetype/utils.py
voicetype/_vendor/__init__.py
voicetype/assets/imgs/__init__.py
voicetype/assets/imgs/aqua-bg-mic.png
voicetype/assets/imgs/blue-bg-mic.png
voicetype/assets/imgs/green-bg-mic.png
voicetype/assets/imgs/mic.png
voicetype/assets/imgs/mic.svg
voicetype/assets/imgs/orange-bg-mic.png
voicetype/assets/imgs/pink-bg-mic.png
voicetype/assets/imgs/red-bg-mic.png
voicetype/assets/imgs/yellow-bg-mic.png
voicetype/assets/imgs/yellow-splotch-logo.png
voicetype/assets/sounds/__init__.py
voicetype/assets/sounds/empty.wav
voicetype/assets/sounds/error.wav
voicetype/assets/sounds/start-record.wav
voicetype/hotkey_listener/hotkey_listener.py
voicetype/hotkey_listener/linux_x11_hotkey_listener.py
voicetype/hotkey_listener/pynput_hotkey_listener.py
voicetype/pipeline/__init__.py
voicetype/pipeline/context.py
voicetype/pipeline/hotkey_dispatcher.py
voicetype/pipeline/pipeline_executor.py
voicetype/pipeline/pipeline_manager.py
voicetype/pipeline/resource_manager.py
voicetype/pipeline/stage_registry.py
voicetype/pipeline/trigger_events.py
voicetype/pipeline/stages/__init__.py
voicetype/pipeline/stages/record_audio.py
voicetype/pipeline/stages/transcribe.py
voicetype/pipeline/stages/type_text.py
voicetype2-0.1.6.dist-info/METADATA
voicetype2-0.1.6.dist-info/WHEEL
voicetype2-0.1.6.dist-info/entry_points.txt
voicetype2-0.1.6.dist-info/licenses/LICENSE
voicetype2-0.1.6.dist-info/RECORD
