Metadata-Version: 2.4
Name: voiceType2
Version: 0.1.6
Summary: Type with your voice using hotkey-activated speech recognition
Author: Adam Lewis
License-Expression: Apache-2.0
License-File: LICENSE
Keywords: accessibility,speech-recognition,transcription,voice-typing
Classifier: Development Status :: 4 - Beta
Classifier: Intended Audience :: End Users/Desktop
Classifier: License :: OSI Approved :: Apache Software License
Classifier: Operating System :: Microsoft :: Windows
Classifier: Operating System :: POSIX :: Linux
Classifier: Programming Language :: Python :: 3
Classifier: Programming Language :: Python :: 3.11
Classifier: Programming Language :: Python :: 3.12
Classifier: Topic :: Multimedia :: Sound/Audio :: Speech
Classifier: Topic :: Text Processing
Requires-Python: <=3.12
Provides-Extra: dev
Requires-Dist: pre-commit; extra == 'dev'
Requires-Dist: pytest; extra == 'dev'
